{
    "hobbies_details": "tennis,golf gardening,travel,grandchildren", 
    "rating": [
        {
            "comment": "Camera angle", 
            "component": 1, 
            "session": 1, 
            "video": "B", 
            "audio": "A", 
            "id": 2494
        }, 
        {
            "comment": "Camera angle", 
            "component": 2, 
            "session": 1, 
            "video": "B", 
            "audio": "A", 
            "id": 2495
        }, 
        {
            "comment": "Camera angle", 
            "component": 3, 
            "session": 1, 
            "video": "B", 
            "audio": "A", 
            "id": 2496
        }, 
        {
            "comment": "Camera angle", 
            "component": 4, 
            "session": 1, 
            "video": "B", 
            "audio": "A", 
            "id": 2497
        }, 
        {
            "comment": "Camera angle", 
            "component": 5, 
            "session": 1, 
            "video": "B", 
            "audio": "A", 
            "id": 2498
        }, 
        {
            "comment": "Camera angle", 
            "component": 9, 
            "session": 1, 
            "video": "B", 
            "audio": "A", 
            "id": 2499
        }, 
        {
            "comment": "Camera angle", 
            "component": 11, 
            "session": 1, 
            "video": "B", 
            "audio": "A", 
            "id": 2500
        }
    ], 
    "education_level": "Bachelor Degree", 
    "mother_cultural_heritage": "North-West European", 
    "consent": true, 
    "mother_education_level": "Diploma", 
    "is_smoker": false, 
    "father_pob_country": "AU", 
    "mother_pob_state": "uk", 
    "student_enrollment": null, 
    "gender": "M", 
    "father_education_level": "TAFE Certificate", 
    "first_language": "english", 
    "id": 169, 
    "student_course": null, 
    "has_piercings": false, 
    "professional_qualification": "BSC(Hons)", 
    "vocal_training_details": "", 
    "other_languages": "Indonesia (sedikit)", 
    "has_hearing_problems": false, 
    "religion": "Protestant", 
    "education_history": [
        {
            "age_to": 8, 
            "age_from": 5, 
            "name": "streaky bay primary school", 
            "id": 678
        }, 
        {
            "age_to": 9, 
            "age_from": 8, 
            "name": "edwardstown primary school", 
            "id": 679
        }, 
        {
            "age_to": 10, 
            "age_from": 9, 
            "name": "tooperang primary school", 
            "id": 680
        }, 
        {
            "age_to": 15, 
            "age_from": 10, 
            "name": "Kings College(now pembroke)Adelaide", 
            "id": 681
        }, 
        {
            "age_to": 23, 
            "age_from": 17, 
            "name": "UNIVERSITY OF ADELAIDE", 
            "id": 682
        }, 
        {
            "age_to": 35, 
            "age_from": 35, 
            "name": "aus grad.man.school UNSW", 
            "id": 683
        }
    ], 
    "location": {
        "city": "Brisbane", 
        "state": "QLD", 
        "name": "University of Queensland", 
        "id": 12
    }, 
    "animal": {
        "name": "Scarlet-chested Parrot", 
        "id": 738
    }, 
    "reading_problems_details": "", 
    "has_dentures": false, 
    "is_student": false, 
    "has_speech_problems": false, 
    "is_left_handed": false, 
    "father_accent": "australia", 
    "RA": {
        "username": "nahyun", 
        "first_name": "", 
        "last_name": "nahyun", 
        "is_active": true, 
        "email": "nahyun.kwon@uqconnect.edu.au", 
        "is_superuser": false, 
        "is_staff": true, 
        "last_login": "2012-11-06 15:25:10", 
        "id": 12, 
        "date_joined": "2011-06-30 13:56:05"
    }, 
    "father_pob_town": "clunes", 
    "professional_occupation": "Geologist and Mining Executive", 
    "father_professional_category": "tradesperson", 
    "profession_history": [
        {
            "age_to": 33, 
            "less_than_a_year": false, 
            "age_from": 23, 
            "id": 503, 
            "name": "Geologist"
        }, 
        {
            "age_to": 70, 
            "less_than_a_year": false, 
            "age_from": 33, 
            "id": 504, 
            "name": "Mining executive"
        }
    ], 
    "has_health_problems": false, 
    "has_reading_problems": false, 
    "collection": "austalk", 
    "pob_state": "S A", 
    "mother_professional_category": "professional", 
    "piercings_details": "", 
    "language_usage": [
        {
            "situation": "coal exploration", 
            "frequency": 10, 
            "name": "Indonesian", 
            "id": 163
        }
    ], 
    "student_aspiration": null, 
    "mother_pob_town": "newcastle on tyne", 
    "residence_history": [
        {
            "town": "ceduna", 
            "age_to": 2, 
            "age_from": 0, 
            "less_than_a_year": false, 
            "country": "AU", 
            "state": "s a "
        }, 
        {
            "town": "streaky bay", 
            "age_to": 9, 
            "age_from": 2, 
            "less_than_a_year": false, 
            "country": "AU", 
            "state": "s a"
        }, 
        {
            "town": "edwardstown", 
            "age_to": 10, 
            "age_from": 9, 
            "less_than_a_year": false, 
            "country": "AU", 
            "state": "s a "
        }, 
        {
            "town": "tooperang", 
            "age_to": 15, 
            "age_from": 10, 
            "less_than_a_year": false, 
            "country": "AU", 
            "state": "s a"
        }, 
        {
            "town": "adelaide", 
            "age_to": 27, 
            "age_from": 15, 
            "less_than_a_year": false, 
            "country": "AU", 
            "state": "s a"
        }, 
        {
            "town": "mt isa", 
            "age_to": 32, 
            "age_from": 27, 
            "less_than_a_year": false, 
            "country": "AU", 
            "state": "qld"
        }, 
        {
            "town": "laverton", 
            "age_to": 36, 
            "age_from": 32, 
            "less_than_a_year": false, 
            "country": "AU", 
            "state": "w a "
        }, 
        {
            "town": "adelaide", 
            "age_to": 39, 
            "age_from": 36, 
            "less_than_a_year": false, 
            "country": "AU", 
            "state": "s a"
        }, 
        {
            "town": "coorparoo", 
            "age_to": 73, 
            "age_from": 39, 
            "less_than_a_year": false, 
            "country": "AU", 
            "state": "qld"
        }
    ], 
    "father_pob_state": "vic", 
    "mother_accent": "australian", 
    "father_cultural_heritage": "Australian", 
    "pob_country": "AU", 
    "dob": "1938-04-10", 
    "speech_problems_details": "", 
    "colour": {
        "name": "Gold", 
        "id": 1
    }, 
    "mother_pob_country": "GB", 
    "mother_first_language": "english", 
    "pob_town": "ceduna", 
    "father_first_language": "english", 
    "has_vocal_training": false, 
    "health_problems_details": "", 
    "cultural_heritage": "Australian", 
    "hearing_problems_details": "", 
    "professional_category": "manager and admin", 
    "has_hobbies": true
}