{
    "hobbies_details": "", 
    "rating": [
        {
            "comment": "NOISE", 
            "component": 1, 
            "session": 1, 
            "video": "A", 
            "audio": "B", 
            "id": 1900
        }, 
        {
            "comment": "NOISE", 
            "component": 2, 
            "session": 1, 
            "video": "A", 
            "audio": "B", 
            "id": 1901
        }, 
        {
            "comment": "NOISE", 
            "component": 3, 
            "session": 1, 
            "video": "A", 
            "audio": "B", 
            "id": 1902
        }, 
        {
            "comment": "NOISE", 
            "component": 4, 
            "session": 1, 
            "video": "A", 
            "audio": "B", 
            "id": 1903
        }, 
        {
            "comment": "NOISE", 
            "component": 5, 
            "session": 1, 
            "video": "A", 
            "audio": "B", 
            "id": 1904
        }, 
        {
            "comment": "NOISE", 
            "component": 9, 
            "session": 1, 
            "video": "A", 
            "audio": "B", 
            "id": 1905
        }, 
        {
            "comment": "NOISE", 
            "component": 11, 
            "session": 1, 
            "video": "A", 
            "audio": "B", 
            "id": 1906
        }, 
        {
            "comment": "", 
            "component": 5, 
            "session": 2, 
            "video": "A", 
            "audio": "A", 
            "id": 1907
        }, 
        {
            "comment": "", 
            "component": 7, 
            "session": 2, 
            "video": "A", 
            "audio": "A", 
            "id": 1908
        }, 
        {
            "comment": "", 
            "component": 9, 
            "session": 2, 
            "video": "A", 
            "audio": "A", 
            "id": 1909
        }, 
        {
            "comment": "", 
            "component": 16, 
            "session": 2, 
            "video": "A", 
            "audio": "A", 
            "id": 1910
        }, 
        {
            "comment": "", 
            "component": 21, 
            "session": 2, 
            "video": "A", 
            "audio": "A", 
            "id": 1911
        }, 
        {
            "comment": "", 
            "component": 22, 
            "session": 2, 
            "video": "A", 
            "audio": "A", 
            "id": 1912
        }, 
        {
            "comment": "", 
            "component": 8, 
            "session": 3, 
            "video": "", 
            "audio": "", 
            "id": 1913
        }, 
        {
            "comment": "", 
            "component": 31, 
            "session": 3, 
            "video": "", 
            "audio": "", 
            "id": 1914
        }, 
        {
            "comment": "", 
            "component": 32, 
            "session": 3, 
            "video": "", 
            "audio": "", 
            "id": 1915
        }
    ], 
    "education_level": "TAFE Certificate", 
    "mother_cultural_heritage": "Australian", 
    "consent": true, 
    "mother_education_level": "Diploma", 
    "is_smoker": false, 
    "father_pob_country": "AU", 
    "mother_pob_state": "SA", 
    "student_enrollment": null, 
    "gender": "F", 
    "father_education_level": "higher school certificate", 
    "first_language": "English", 
    "id": 233, 
    "student_course": null, 
    "has_piercings": false, 
    "professional_qualification": "Certificate in Business Administration", 
    "vocal_training_details": "", 
    "other_languages": "very small amoutn of French", 
    "has_hearing_problems": false, 
    "religion": "nil", 
    "education_history": [
        {
            "age_to": 12, 
            "age_from": 5, 
            "name": "Oaklands Primary School", 
            "id": 884
        }, 
        {
            "age_to": 16, 
            "age_from": 13, 
            "name": "Seacombe HIgh School", 
            "id": 885
        }, 
        {
            "age_to": 53, 
            "age_from": 45, 
            "name": "TAFE - various", 
            "id": 886
        }
    ], 
    "location": {
        "city": "Adelaide", 
        "state": "SA", 
        "name": "Flinders University", 
        "id": 6
    }, 
    "animal": {
        "name": "Spectacled Porpoise", 
        "id": 1164
    }, 
    "reading_problems_details": "", 
    "has_dentures": false, 
    "is_student": false, 
    "has_speech_problems": false, 
    "is_left_handed": false, 
    "father_accent": "nil", 
    "RA": {
        "username": "Tom Anderson", 
        "first_name": "Tom", 
        "last_name": "Anderson", 
        "is_active": true, 
        "email": "tom.anderson@flinders.edu.au", 
        "is_superuser": false, 
        "is_staff": true, 
        "last_login": "2012-12-06 10:50:46", 
        "id": 23, 
        "date_joined": "2011-10-17 10:58:48"
    }, 
    "father_pob_town": "Adelaide", 
    "professional_occupation": "Executive Assistant", 
    "father_professional_category": "manager and admin", 
    "profession_history": [
        {
            "age_to": 33, 
            "less_than_a_year": false, 
            "age_from": 17, 
            "id": 654, 
            "name": "Administration Assistant"
        }, 
        {
            "age_to": 37, 
            "less_than_a_year": false, 
            "age_from": 35, 
            "id": 655, 
            "name": "home-based child carer"
        }, 
        {
            "age_to": 58, 
            "less_than_a_year": false, 
            "age_from": 38, 
            "id": 656, 
            "name": "Executive Assistant"
        }
    ], 
    "has_health_problems": false, 
    "has_reading_problems": false, 
    "collection": "austalk", 
    "pob_state": "South Aust", 
    "mother_professional_category": "home duties", 
    "piercings_details": "", 
    "language_usage": [
        {
            "situation": "all", 
            "frequency": 100, 
            "name": "English", 
            "id": 240
        }
    ], 
    "student_aspiration": null, 
    "mother_pob_town": "Adelaide", 
    "residence_history": [
        {
            "town": "Adelaide", 
            "age_to": 27, 
            "age_from": 0, 
            "less_than_a_year": false, 
            "country": "AU", 
            "state": "SA"
        }, 
        {
            "town": "Darwin", 
            "age_to": 31, 
            "age_from": 27, 
            "less_than_a_year": false, 
            "country": "AU", 
            "state": "NT"
        }, 
        {
            "town": "Adelaide", 
            "age_to": 58, 
            "age_from": 32, 
            "less_than_a_year": false, 
            "country": "AU", 
            "state": "SA"
        }
    ], 
    "father_pob_state": "SA", 
    "mother_accent": "nil", 
    "father_cultural_heritage": "Australian", 
    "pob_country": "AU", 
    "dob": "1953-09-30", 
    "speech_problems_details": "", 
    "colour": {
        "name": "Green", 
        "id": 2
    }, 
    "mother_pob_country": "AU", 
    "mother_first_language": "English", 
    "pob_town": "Glenelg", 
    "father_first_language": "English", 
    "has_vocal_training": false, 
    "health_problems_details": "", 
    "cultural_heritage": "Australian", 
    "hearing_problems_details": "", 
    "professional_category": "clerical and service", 
    "has_hobbies": false
}