{
    "hobbies_details": "art (painting), choirs, listening to opera, tennis, watching cricket, University of the Third Age", 
    "rating": [
        {
            "comment": "", 
            "component": 1, 
            "session": 1, 
            "video": "A", 
            "audio": "A", 
            "id": 782
        }, 
        {
            "comment": "", 
            "component": 2, 
            "session": 1, 
            "video": "A", 
            "audio": "A", 
            "id": 783
        }, 
        {
            "comment": "", 
            "component": 3, 
            "session": 1, 
            "video": "A", 
            "audio": "A", 
            "id": 784
        }, 
        {
            "comment": "", 
            "component": 4, 
            "session": 1, 
            "video": "A", 
            "audio": "A", 
            "id": 785
        }, 
        {
            "comment": "", 
            "component": 5, 
            "session": 1, 
            "video": "A", 
            "audio": "A", 
            "id": 786
        }, 
        {
            "comment": "", 
            "component": 9, 
            "session": 1, 
            "video": "A", 
            "audio": "A", 
            "id": 787
        }, 
        {
            "comment": "", 
            "component": 11, 
            "session": 1, 
            "video": "A", 
            "audio": "A", 
            "id": 788
        }, 
        {
            "comment": "", 
            "component": 8, 
            "session": 3, 
            "video": "A", 
            "audio": "A", 
            "id": 789
        }, 
        {
            "comment": "", 
            "component": 31, 
            "session": 3, 
            "video": "A", 
            "audio": "A", 
            "id": 790
        }, 
        {
            "comment": "", 
            "component": 32, 
            "session": 3, 
            "video": "A", 
            "audio": "A", 
            "id": 791
        }
    ], 
    "education_level": "Bachelor Degree", 
    "mother_cultural_heritage": "Australian", 
    "consent": true, 
    "mother_education_level": "school certificate", 
    "is_smoker": false, 
    "father_pob_country": "AU", 
    "mother_pob_state": "NSW", 
    "student_enrollment": null, 
    "gender": "F", 
    "father_education_level": "TAFE Certificate", 
    "first_language": "English", 
    "id": 273, 
    "student_course": null, 
    "has_piercings": false, 
    "professional_qualification": "", 
    "vocal_training_details": "singing lessons and singing in choirs", 
    "other_languages": "School Latin and French", 
    "has_hearing_problems": false, 
    "religion": "", 
    "education_history": [
        {
            "age_to": 7, 
            "age_from": 5, 
            "name": "Lakemba Primary School", 
            "id": 1057
        }, 
        {
            "age_to": 9, 
            "age_from": 7, 
            "name": "Southerland Primary School", 
            "id": 1058
        }, 
        {
            "age_to": 12, 
            "age_from": 10, 
            "name": "Hurtsville Primary School Opportunity Class for the Specially Intelligent", 
            "id": 1059
        }, 
        {
            "age_to": 15, 
            "age_from": 13, 
            "name": "St George Girls High School", 
            "id": 1060
        }, 
        {
            "age_to": 35, 
            "age_from": 34, 
            "name": "evening college", 
            "id": 1061
        }, 
        {
            "age_to": 41, 
            "age_from": 36, 
            "name": "Sydney University", 
            "id": 1062
        }, 
        {
            "age_to": 55, 
            "age_from": 53, 
            "name": "Monash University", 
            "id": 1063
        }
    ], 
    "location": {
        "city": "Canberra", 
        "state": "ACT", 
        "name": "Australian National University", 
        "id": 1
    }, 
    "animal": {
        "name": "Eastern Quoll", 
        "id": 995
    }, 
    "reading_problems_details": "", 
    "has_dentures": false, 
    "is_student": false, 
    "has_speech_problems": false, 
    "is_left_handed": false, 
    "father_accent": "Australian", 
    "RA": {
        "username": "katharine gosling", 
        "first_name": "katharine", 
        "last_name": "gosling", 
        "is_active": true, 
        "email": "katharine.gosling@anu.edu.au", 
        "is_superuser": false, 
        "is_staff": true, 
        "last_login": "2012-10-04 15:49:48", 
        "id": 16, 
        "date_joined": "2011-07-20 12:57:59"
    }, 
    "father_pob_town": "Lakemba", 
    "professional_occupation": "Bank Clerk / Administrator", 
    "father_professional_category": "tradesperson", 
    "profession_history": [
        {
            "age_to": 30, 
            "less_than_a_year": false, 
            "age_from": 15, 
            "id": 753, 
            "name": "stenographer"
        }, 
        {
            "age_to": 46, 
            "less_than_a_year": false, 
            "age_from": 30, 
            "id": 754, 
            "name": "bank clek"
        }, 
        {
            "age_to": 62, 
            "less_than_a_year": false, 
            "age_from": 46, 
            "id": 755, 
            "name": "TAFE administrator"
        }
    ], 
    "has_health_problems": false, 
    "has_reading_problems": false, 
    "collection": "austalk", 
    "pob_state": "NSW", 
    "mother_professional_category": "home duties", 
    "piercings_details": "", 
    "language_usage": [
        {
            "situation": "every day life", 
            "frequency": 100, 
            "name": "English", 
            "id": 295
        }
    ], 
    "student_aspiration": null, 
    "mother_pob_town": "Goulburn", 
    "residence_history": [
        {
            "town": "Lakemba", 
            "age_to": 7, 
            "age_from": 0, 
            "less_than_a_year": false, 
            "country": "AU", 
            "state": "NSW"
        }, 
        {
            "town": "Jannali", 
            "age_to": 9, 
            "age_from": 7, 
            "less_than_a_year": false, 
            "country": "AU", 
            "state": "NSW"
        }, 
        {
            "town": "Cooma", 
            "age_to": 9, 
            "age_from": 9, 
            "less_than_a_year": true, 
            "country": "AU", 
            "state": "NSW"
        }, 
        {
            "town": "Connell's Point", 
            "age_to": 45, 
            "age_from": 10, 
            "less_than_a_year": false, 
            "country": "AU", 
            "state": "NSW"
        }, 
        {
            "town": "North Sydney", 
            "age_to": 52, 
            "age_from": 46, 
            "less_than_a_year": false, 
            "country": "AU", 
            "state": "NSW"
        }, 
        {
            "town": "Melbourne", 
            "age_to": 56, 
            "age_from": 53, 
            "less_than_a_year": false, 
            "country": "AU", 
            "state": "VIC"
        }, 
        {
            "town": "Mollymook", 
            "age_to": 74, 
            "age_from": 57, 
            "less_than_a_year": false, 
            "country": "AU", 
            "state": "NSW"
        }, 
        {
            "town": "Canberra", 
            "age_to": 79, 
            "age_from": 74, 
            "less_than_a_year": false, 
            "country": "AU", 
            "state": "ACT"
        }
    ], 
    "father_pob_state": "NSW", 
    "mother_accent": "Austrailan", 
    "father_cultural_heritage": "Australian", 
    "pob_country": "AU", 
    "dob": "1932-11-14", 
    "speech_problems_details": "", 
    "colour": {
        "name": "Red", 
        "id": 3
    }, 
    "mother_pob_country": "AU", 
    "mother_first_language": "English", 
    "pob_town": "Lakemba", 
    "father_first_language": "English", 
    "has_vocal_training": true, 
    "health_problems_details": "", 
    "cultural_heritage": "Australian", 
    "hearing_problems_details": "", 
    "professional_category": "manager and admin", 
    "has_hobbies": true
}